{
  "cityList": [
    {
      "name": "Москва",
      "address":[
        {"name": "Большая Бронная улица, 29"},
        {"name": "улица Сергия Радонежского, 6"},
        {"name": "улица Щипок, 13с1"},
        {"name": "Усачёва улица, 19Ак1"}
      ]
    },
    {
      "name": "Ульяновск",
      "address": [
        {"name": "Соборная площадь, 1"},
        {"name":"улица Урицкого, 29"},
        {"name":"Ленинградская улица, 5"},
        {"name":"Заводской проезд, 27"}
      ]
    },
    {
      "name": "Новосибирск",
      "address": [
        {"name":"улица Кирова, 3"},
        {"name":"улица Мичурина, 12"},
        {"name":"Большевистская улица, 14"},
        {"name":"проспект Карла Маркса, 37/2"}
      ]
    },
    {
      "name": "Иркутск",
      "address": [
        {"name": "улица 5-й Армии, 29"},
        {"name":"улица Литвинова, 17"},
        {"name":"улица Пушкина, 25"},
        {"name":"улица Игошина, 22"}
      ]
    }
  ]
}
